ccf/__init__.py
ccf/_versionifier.py
ccf/cose.py
ccf/ledger.py
ccf/ledger_code.py
ccf/ledger_viz.py
ccf/merkletree.py
ccf/py.typed
ccf/read_ledger.py
ccf/receipt.py
ccf/split_ledger.py
ccf/tx_id.py
ccf/verify_ledger_secrets_chain.py
ccf-6.0.20.data/scripts/keygenerator.sh
ccf-6.0.20.data/scripts/submit_recovery_share.sh
ccf-6.0.20.dist-info/licenses/LICENSE
ccf-6.0.20.dist-info/METADATA
ccf-6.0.20.dist-info/WHEEL
ccf-6.0.20.dist-info/entry_points.txt
ccf-6.0.20.dist-info/top_level.txt
ccf-6.0.20.dist-info/RECORD
